Workbook

Sheet Dashboard
A1: Profit Dashboard – FREE Lite
A2: Start month | B2: 46266
A4: Month | B4: Orders | C4: Revenue $ | D4: Platform fees $ | E4: Order profit $ | F4: Margin
A5: =B2 | B5: =COUNTIFS(Orders!$N$2:$N$31,$A5) | C5: =SUMIFS(Orders!$K$2:$K$31,Orders!$N$2:$N$31,$A5) | D5: =SUMIFS(Orders!$L$2:$L$31,Orders!$N$2:$N$31,$A5) | E5: =SUMIFS(Orders!$M$2:$M$31,Orders!$N$2:$N$31,$A5) | F5: =IF(C5=0,0,E5/C5)
A6: =EDATE(A5,1) | B6: =COUNTIFS(Orders!$N$2:$N$31,$A6) | C6: =SUMIFS(Orders!$K$2:$K$31,Orders!$N$2:$N$31,$A6) | D6: =SUMIFS(Orders!$L$2:$L$31,Orders!$N$2:$N$31,$A6) | E6: =SUMIFS(Orders!$M$2:$M$31,Orders!$N$2:$N$31,$A6) | F6: =IF(C6=0,0,E6/C6)
A7: =EDATE(A6,1) | B7: =COUNTIFS(Orders!$N$2:$N$31,$A7) | C7: =SUMIFS(Orders!$K$2:$K$31,Orders!$N$2:$N$31,$A7) | D7: =SUMIFS(Orders!$L$2:$L$31,Orders!$N$2:$N$31,$A7) | E7: =SUMIFS(Orders!$M$2:$M$31,Orders!$N$2:$N$31,$A7) | F7: =IF(C7=0,0,E7/C7)
A8: =EDATE(A7,1) | B8: =COUNTIFS(Orders!$N$2:$N$31,$A8) | C8: =SUMIFS(Orders!$K$2:$K$31,Orders!$N$2:$N$31,$A8) | D8: =SUMIFS(Orders!$L$2:$L$31,Orders!$N$2:$N$31,$A8) | E8: =SUMIFS(Orders!$M$2:$M$31,Orders!$N$2:$N$31,$A8) | F8: =IF(C8=0,0,E8/C8)
A9: =EDATE(A8,1) | B9: =COUNTIFS(Orders!$N$2:$N$31,$A9) | C9: =SUMIFS(Orders!$K$2:$K$31,Orders!$N$2:$N$31,$A9) | D9: =SUMIFS(Orders!$L$2:$L$31,Orders!$N$2:$N$31,$A9) | E9: =SUMIFS(Orders!$M$2:$M$31,Orders!$N$2:$N$31,$A9) | F9: =IF(C9=0,0,E9/C9)
A10: =EDATE(A9,1) | B10: =COUNTIFS(Orders!$N$2:$N$31,$A10) | C10: =SUMIFS(Orders!$K$2:$K$31,Orders!$N$2:$N$31,$A10) | D10: =SUMIFS(Orders!$L$2:$L$31,Orders!$N$2:$N$31,$A10) | E10: =SUMIFS(Orders!$M$2:$M$31,Orders!$N$2:$N$31,$A10) | F10: =IF(C10=0,0,E10/C10)
A11: =EDATE(A10,1) | B11: =COUNTIFS(Orders!$N$2:$N$31,$A11) | C11: =SUMIFS(Orders!$K$2:$K$31,Orders!$N$2:$N$31,$A11) | D11: =SUMIFS(Orders!$L$2:$L$31,Orders!$N$2:$N$31,$A11) | E11: =SUMIFS(Orders!$M$2:$M$31,Orders!$N$2:$N$31,$A11) | F11: =IF(C11=0,0,E11/C11)
A12: =EDATE(A11,1) | B12: =COUNTIFS(Orders!$N$2:$N$31,$A12) | C12: =SUMIFS(Orders!$K$2:$K$31,Orders!$N$2:$N$31,$A12) | D12: =SUMIFS(Orders!$L$2:$L$31,Orders!$N$2:$N$31,$A12) | E12: =SUMIFS(Orders!$M$2:$M$31,Orders!$N$2:$N$31,$A12) | F12: =IF(C12=0,0,E12/C12)
A13: =EDATE(A12,1) | B13: =COUNTIFS(Orders!$N$2:$N$31,$A13) | C13: =SUMIFS(Orders!$K$2:$K$31,Orders!$N$2:$N$31,$A13) | D13: =SUMIFS(Orders!$L$2:$L$31,Orders!$N$2:$N$31,$A13) | E13: =SUMIFS(Orders!$M$2:$M$31,Orders!$N$2:$N$31,$A13) | F13: =IF(C13=0,0,E13/C13)
A14: =EDATE(A13,1) | B14: =COUNTIFS(Orders!$N$2:$N$31,$A14) | C14: =SUMIFS(Orders!$K$2:$K$31,Orders!$N$2:$N$31,$A14) | D14: =SUMIFS(Orders!$L$2:$L$31,Orders!$N$2:$N$31,$A14) | E14: =SUMIFS(Orders!$M$2:$M$31,Orders!$N$2:$N$31,$A14) | F14: =IF(C14=0,0,E14/C14)
A15: =EDATE(A14,1) | B15: =COUNTIFS(Orders!$N$2:$N$31,$A15) | C15: =SUMIFS(Orders!$K$2:$K$31,Orders!$N$2:$N$31,$A15) | D15: =SUMIFS(Orders!$L$2:$L$31,Orders!$N$2:$N$31,$A15) | E15: =SUMIFS(Orders!$M$2:$M$31,Orders!$N$2:$N$31,$A15) | F15: =IF(C15=0,0,E15/C15)
A16: =EDATE(A15,1) | B16: =COUNTIFS(Orders!$N$2:$N$31,$A16) | C16: =SUMIFS(Orders!$K$2:$K$31,Orders!$N$2:$N$31,$A16) | D16: =SUMIFS(Orders!$L$2:$L$31,Orders!$N$2:$N$31,$A16) | E16: =SUMIFS(Orders!$M$2:$M$31,Orders!$N$2:$N$31,$A16) | F16: =IF(C16=0,0,E16/C16)
A18: Total | B18: =SUM(B5:B16) | C18: =SUM(C5:C16) | D18: =SUM(D5:D16) | E18: =SUM(E5:E16)
A20: Want inventory, refunds, expenses, a weekly view and charts? Get the full Side Hustle Bookkeeping & Profit Tracker ($9).

Sheet Orders
A1: Date | B1: Order ID | C1: Channel | D1: Product | E1: Qty | F1: Unit price $ | G1: Unit cost $ | H1: Fee % | I1: Fixed fee $ | J1: Shipping $ | K1: Revenue $ | L1: Platform fees $ | M1: Order profit $ | N1: Month
A2: 46286 | B2: SAMPLE-1001 | C2: Stripe | D2: SAMPLE Candle - Cedar | E2: 2 | F2: 17.1 | G2: 4.5 | H2: 0.029 | I2: 0.3 | J2: 0 | K2: =IF(E2="","",E2*F2) | L2: =IF(E2="","",ROUND(K2*H2+I2,2)) | M2: =IF(E2="","",K2-E2*G2-L2-N(J2)) | N2: =IF(A2="","",DATE(YEAR(A2),MONTH(A2),1))
A3: 46270 | B3: SAMPLE-1002 | C3: Shopify | D3: SAMPLE Tote Bag | E3: 1 | F3: 24 | G3: 6 | H3: 0.029 | I3: 0.3 | J3: 0 | K3: =IF(E3="","",E3*F3) | L3: =IF(E3="","",ROUND(K3*H3+I3,2)) | M3: =IF(E3="","",K3-E3*G3-L3-N(J3)) | N3: =IF(A3="","",DATE(YEAR(A3),MONTH(A3),1))
A4: 46298 | B4: SAMPLE-1003 | C4: Etsy | D4: SAMPLE Candle - Cedar | E4: 1 | F4: 19 | G4: 4.5 | H4: 0.095 | I4: 0.45 | J4: 4.5 | K4: =IF(E4="","",E4*F4) | L4: =IF(E4="","",ROUND(K4*H4+I4,2)) | M4: =IF(E4="","",K4-E4*G4-L4-N(J4)) | N4: =IF(A4="","",DATE(YEAR(A4),MONTH(A4),1))
A5: 46292 | B5: SAMPLE-1004 | C5: Etsy | D5: SAMPLE Candle - Lavender | E5: 1 | F5: 18 | G5: 4.2 | H5: 0.095 | I5: 0.45 | J5: 4.5 | K5: =IF(E5="","",E5*F5) | L5: =IF(E5="","",ROUND(K5*H5+I5,2)) | M5: =IF(E5="","",K5-E5*G5-L5-N(J5)) | N5: =IF(A5="","",DATE(YEAR(A5),MONTH(A5),1))
A6: 46269 | B6: SAMPLE-1005 | C6: Etsy | D6: SAMPLE Tote Bag | E6: 1 | F6: 24 | G6: 6 | H6: 0.095 | I6: 0.45 | J6: 0 | K6: =IF(E6="","",E6*F6) | L6: =IF(E6="","",ROUND(K6*H6+I6,2)) | M6: =IF(E6="","",K6-E6*G6-L6-N(J6)) | N6: =IF(A6="","",DATE(YEAR(A6),MONTH(A6),1))
A7: 46302 | B7: SAMPLE-1006 | C7: Etsy | D7: SAMPLE Tote Bag | E7: 2 | F7: 24 | G7: 6 | H7: 0.095 | I7: 0.45 | J7: 2.5 | K7: =IF(E7="","",E7*F7) | L7: =IF(E7="","",ROUND(K7*H7+I7,2)) | M7: =IF(E7="","",K7-E7*G7-L7-N(J7)) | N7: =IF(A7="","",DATE(YEAR(A7),MONTH(A7),1))
A8: 46268 | B8: SAMPLE-1007 | C8: Shopify | D8: SAMPLE Tote Bag | E8: 1 | F8: 24 | G8: 6 | H8: 0.029 | I8: 0.3 | J8: 4.5 | K8: =IF(E8="","",E8*F8) | L8: =IF(E8="","",ROUND(K8*H8+I8,2)) | M8: =IF(E8="","",K8-E8*G8-L8-N(J8)) | N8: =IF(A8="","",DATE(YEAR(A8),MONTH(A8),1))
A9: 46275 | B9: SAMPLE-1008 | C9: eBay | D9: SAMPLE Tote Bag | E9: 1 | F9: 21.6 | G9: 6 | H9: 0.13 | I9: 0.3 | J9: 3.8 | K9: =IF(E9="","",E9*F9) | L9: =IF(E9="","",ROUND(K9*H9+I9,2)) | M9: =IF(E9="","",K9-E9*G9-L9-N(J9)) | N9: =IF(A9="","",DATE(YEAR(A9),MONTH(A9),1))
A10: 46301 | B10: SAMPLE-1009 | C10: eBay | D10: SAMPLE Candle - Cedar | E10: 1 | F10: 19 | G10: 4.5 | H10: 0.13 | I10: 0.3 | J10: 2.5 | K10: =IF(E10="","",E10*F10) | L10: =IF(E10="","",ROUND(K10*H10+I10,2)) | M10: =IF(E10="","",K10-E10*G10-L10-N(J10)) | N10: =IF(A10="","",DATE(YEAR(A10),MONTH(A10),1))
A11: 46289 | B11: SAMPLE-1010 | C11: Stripe | D11: SAMPLE Candle - Lavender | E11: 3 | F11: 18 | G11: 4.2 | H11: 0.029 | I11: 0.3 | J11: 0 | K11: =IF(E11="","",E11*F11) | L11: =IF(E11="","",ROUND(K11*H11+I11,2)) | M11: =IF(E11="","",K11-E11*G11-L11-N(J11)) | N11: =IF(A11="","",DATE(YEAR(A11),MONTH(A11),1))
A12: 46302 | B12: SAMPLE-1011 | C12: Etsy | D12: SAMPLE Candle - Lavender | E12: 3 | F12: 18 | G12: 4.2 | H12: 0.095 | I12: 0.45 | J12: 4.5 | K12: =IF(E12="","",E12*F12) | L12: =IF(E12="","",ROUND(K12*H12+I12,2)) | M12: =IF(E12="","",K12-E12*G12-L12-N(J12)) | N12: =IF(A12="","",DATE(YEAR(A12),MONTH(A12),1))
A13: 46300 | B13: SAMPLE-1012 | C13: Amazon | D13: SAMPLE Sticker Pack | E13: 1 | F13: 6 | G13: 1.1 | H13: 0.15 | I13: 0 | J13: 4.5 | K13: =IF(E13="","",E13*F13) | L13: =IF(E13="","",ROUND(K13*H13+I13,2)) | M13: =IF(E13="","",K13-E13*G13-L13-N(J13)) | N13: =IF(A13="","",DATE(YEAR(A13),MONTH(A13),1))
K14: =IF(E14="","",E14*F14) | L14: =IF(E14="","",ROUND(K14*H14+I14,2)) | M14: =IF(E14="","",K14-E14*G14-L14-N(J14)) | N14: =IF(A14="","",DATE(YEAR(A14),MONTH(A14),1))
K15: =IF(E15="","",E15*F15) | L15: =IF(E15="","",ROUND(K15*H15+I15,2)) | M15: =IF(E15="","",K15-E15*G15-L15-N(J15)) | N15: =IF(A15="","",DATE(YEAR(A15),MONTH(A15),1))
K16: =IF(E16="","",E16*F16) | L16: =IF(E16="","",ROUND(K16*H16+I16,2)) | M16: =IF(E16="","",K16-E16*G16-L16-N(J16)) | N16: =IF(A16="","",DATE(YEAR(A16),MONTH(A16),1))
K17: =IF(E17="","",E17*F17) | L17: =IF(E17="","",ROUND(K17*H17+I17,2)) | M17: =IF(E17="","",K17-E17*G17-L17-N(J17)) | N17: =IF(A17="","",DATE(YEAR(A17),MONTH(A17),1))
K18: =IF(E18="","",E18*F18) | L18: =IF(E18="","",ROUND(K18*H18+I18,2)) | M18: =IF(E18="","",K18-E18*G18-L18-N(J18)) | N18: =IF(A18="","",DATE(YEAR(A18),MONTH(A18),1))
K19: =IF(E19="","",E19*F19) | L19: =IF(E19="","",ROUND(K19*H19+I19,2)) | M19: =IF(E19="","",K19-E19*G19-L19-N(J19)) | N19: =IF(A19="","",DATE(YEAR(A19),MONTH(A19),1))
K20: =IF(E20="","",E20*F20) | L20: =IF(E20="","",ROUND(K20*H20+I20,2)) | M20: =IF(E20="","",K20-E20*G20-L20-N(J20)) | N20: =IF(A20="","",DATE(YEAR(A20),MONTH(A20),1))
K21: =IF(E21="","",E21*F21) | L21: =IF(E21="","",ROUND(K21*H21+I21,2)) | M21: =IF(E21="","",K21-E21*G21-L21-N(J21)) | N21: =IF(A21="","",DATE(YEAR(A21),MONTH(A21),1))
K22: =IF(E22="","",E22*F22) | L22: =IF(E22="","",ROUND(K22*H22+I22,2)) | M22: =IF(E22="","",K22-E22*G22-L22-N(J22)) | N22: =IF(A22="","",DATE(YEAR(A22),MONTH(A22),1))
K23: =IF(E23="","",E23*F23) | L23: =IF(E23="","",ROUND(K23*H23+I23,2)) | M23: =IF(E23="","",K23-E23*G23-L23-N(J23)) | N23: =IF(A23="","",DATE(YEAR(A23),MONTH(A23),1))
K24: =IF(E24="","",E24*F24) | L24: =IF(E24="","",ROUND(K24*H24+I24,2)) | M24: =IF(E24="","",K24-E24*G24-L24-N(J24)) | N24: =IF(A24="","",DATE(YEAR(A24),MONTH(A24),1))
K25: =IF(E25="","",E25*F25) | L25: =IF(E25="","",ROUND(K25*H25+I25,2)) | M25: =IF(E25="","",K25-E25*G25-L25-N(J25)) | N25: =IF(A25="","",DATE(YEAR(A25),MONTH(A25),1))
... K31: =IF(E31="","",E31*F31) | L31: =IF(E31="","",ROUND(K31*H31+I31,2)) | M31: =IF(E31="","",K31-E31*G31-L31-N(J31)) | N31: =IF(A31="","",DATE(YEAR(A31),MONTH(A31),1))
A33: Free Lite version: 30 order rows, 1 tab. Sample rows are fictional – delete them. Fee rates are examples; use your own.
A34: Full version ($9): 500 orders, live inventory & reorder alerts, refunds (restock-aware), expenses, weekly dashboard + charts, auto fee lookup by channel.
